[
  {
    "id": "standard_sla",
    "name": "Standard SLA",
    "description": "Default SLA policy for most customers",
    "priority_overrides": {
      "P1": {
        "first_response_minutes": 15,
        "resolution_minutes": 240
      },
      "P2": {
        "first_response_minutes": 60,
        "resolution_minutes": 480
      },
      "P3": {
        "first_response_minutes": 240,
        "resolution_minutes": 1440
      },
      "P4": {
        "first_response_minutes": 480,
        "resolution_minutes": 2880
      }
    },
    "business_hours_only": true,
    "escalation_enabled": true
  },
  {
    "id": "premium_sla",
    "name": "Premium SLA",
    "description": "Enhanced SLA for premium customers",
    "priority_overrides": {
      "P1": {
        "first_response_minutes": 5,
        "resolution_minutes": 120
      },
      "P2": {
        "first_response_minutes": 30,
        "resolution_minutes": 240
      },
      "P3": {
        "first_response_minutes": 120,
        "resolution_minutes": 720
      },
      "P4": {
        "first_response_minutes": 240,
        "resolution_minutes": 1440
      }
    },
    "business_hours_only": false,
    "escalation_enabled": true
  },
  {
    "id": "basic_sla",
    "name": "Basic SLA",
    "description": "Basic SLA for free-tier customers",
    "priority_overrides": {
      "P1": {
        "first_response_minutes": 60,
        "resolution_minutes": 720
      },
      "P2": {
        "first_response_minutes": 240,
        "resolution_minutes": 1440
      },
      "P3": {
        "first_response_minutes": 480,
        "resolution_minutes": 2880
      },
      "P4": {
        "first_response_minutes": 720,
        "resolution_minutes": 4320
      }
    },
    "business_hours_only": true,
    "escalation_enabled": false
  }
]